asyncpyspapi/__init__.py
asyncpyspapi/api.py
asyncpyspapi/models.py
asyncpyspapi-2.1.2.dist-info/LICENSE
asyncpyspapi-2.1.2.dist-info/METADATA
asyncpyspapi-2.1.2.dist-info/WHEEL
asyncpyspapi-2.1.2.dist-info/top_level.txt
asyncpyspapi-2.1.2.dist-info/RECORD
