Metadata-Version: 2.1
Name: asyncpyspapi
Version: 2.1.2
Summary: API wrapper for SP servers written in Python
Home-page: https://github.com/kvertisp/asyncpyspapi
Author: deesiigneer & kvertsp
License: MIT
Project-URL: Documentation, https://pyspapi.readthedocs.io/ru/latest/
Project-URL: GitHub, https://github.com/kvertisp/asyncpyspapi
Project-URL: Discord, https://discord.com/invite/VbyHaKRAaN
Requires-Python: >=3.8.0
License-File: LICENSE
Requires-Dist: httpx
